{
    "projects": [
        {
            "id": 0,
            "name": "OnStyle",
            "description": "Um e-commerce integrado com a API do PagSeguro feito usando PHP com a framework Laravel.",
            "source": "https://github.com/nixs-dev/OnStyle",
            "stacks": ["Laravel", "PHP", "MySQL", "JavaScript", "HTML", "CSS"],
            "logo": "logo.png",
            "screenshots": [
                "1.png",
                "2.png",
                "3.png",
                "4.png",
                "5.png"
            ]
        },
        {
            "id": 1,
            "name": "SayUP",
            "description": "Uma plataforma com o objetivo de se fazer pesquisas e eventos científicos. Existe serviço de criação e agendamento de eventos e um sistema de enquetes para critério de pesquisa. O sistema possui diversas categorias, cada uma representando uma área do conhecimento. As pesquisas são feitas através de um sistema de enquetes.",
            "source": "https://github.com/nixs-dev/SayUP",
            "stacks": ["Django", "Python", "HTML", "CSS", "JS", "MySQL"],
            "logo": "logo.png",
            "screenshots": [
                "1.gif",
                "2.png",
                "3.png",
                "4.png",
                "5.png",
				"6.png"
            ]
        },
		{
            "id": 2,
            "name": "VNet",
            "description": "VNet é uma rede social que conta com recursos padrões de uma rede comum: publicações, curtidas, comentários, perfis e um bate-papo.",
            "source": "https://github.com/nixs-dev/VNet",
            "stacks": ["PHP", "Ratchet", "CSS", "HTML", "JS", "MySQL"],
            "logo": "logo.png",
            "screenshots": [
                "1.png",
                "2.png",
                "3.png",
                "4.png",
                "5.png",
				"6.png",
				"7.png",
				"8.png"
            ]
        }
    ],
    "stacks": {
        "html": {
            "name": "HTML",
            "experience": "3 anos",
            "level": "Intermediário"
        },
        "CSS": {
            "name": "CSS",
            "experience": "3 anos",
            "level": "Intermediário"
        },
        "js": {
            "name": "JavaScript",
            "experience": "3 anos",
            "level": "Intermediário"
        },
        "nodejs": {
            "name": "NodeJS",
            "experience": "2 anos",
            "level": "Intermediário"
        },
        "php": {
            "name": "PHP",
            "experience": "3 anos",
            "level": "Intermediário"
        },
        "reactjs": {
            "name": "ReactJS",
            "experience": "1 ano",
            "level": "Iniciante"
        },
        "mysql": {
            "name": "MySQL",
            "experience": "3 anos",
            "level": "Intermediário"
        }
    }
}